bomcheck.py
check_sm_parts.py
bomcheck-2.4.dist-info/licenses/LICENSE.txt
bomcheck-2.4.dist-info/METADATA
bomcheck-2.4.dist-info/WHEEL
bomcheck-2.4.dist-info/entry_points.txt
bomcheck-2.4.dist-info/top_level.txt
bomcheck-2.4.dist-info/RECORD
