Metadata-Version: 2.4
Name: bomcheck
Version: 2.4
Summary: Compare BOMs stored in Excel files
Author-email: Ken Carlton <kencarlton55@gmail.com>
Maintainer-email: Ken Carlton <kencarlton55@gmail.com>
License: GPL-3.0-or-later
Project-URL: Homepage, https://github.com/kcarlton55/bomcheck
Keywords: BOM,BOMs,compare,bill,materials,SolidWorks,SyteLine,ERP,CAD
Classifier: Programming Language :: Python :: 3
Classifier: Development Status :: 5 - Production/Stable
Classifier: Natural Language :: English
Classifier: License :: OSI Approved :: GNU General Public License v3 (GPLv3)
Classifier: Intended Audience :: Manufacturing
Classifier: Intended Audience :: End Users/Desktop
Classifier: Operating System :: OS Independent
Requires-Python: >=3.8
License-File: LICENSE.txt
Requires-Dist: tomli>=1.1.0
Requires-Dist: pandas>=1.2
Requires-Dist: openpyxl>=3.0
Requires-Dist: requests>=2.29
Requires-Dist: xlsxwriter>=3.2.9
Dynamic: license-file
